takara/conf.py
takara/exc.py
takara/scripts.py
takara/version.py
takara/takara/init.py
takara/takara/migrate.py
takara/takara/cipher/fernet.py
takara/takara/seal/passwd.py
takara/takara/seal/shamir.py
takara/takara/store/file_store.py
takara-1.2.dist-info/LICENSE
takara-1.2.dist-info/METADATA
takara-1.2.dist-info/WHEEL
takara-1.2.dist-info/entry_points.txt
takara-1.2.dist-info/top_level.txt
takara-1.2.dist-info/RECORD
